README.md
setup.py
panamap_proto/__init__.py
panamap_proto/panamap_proto.py
panamap_proto/panamap_proto.version
panamap_proto.egg-info/PKG-INFO
panamap_proto.egg-info/SOURCES.txt
panamap_proto.egg-info/dependency_links.txt
panamap_proto.egg-info/requires.txt
panamap_proto.egg-info/top_level.txt