Metadata-Version: 2.1
Name: panamap-proto
Version: 1.1.1
Summary: Protobuf module for panamap
Home-page: https://github.com/panamap-object-mapper/panamap-proto
Author: Kirill Sulim
Author-email: kirillsulim@gmail.com
License: MIT
Keywords: object mapper,protobuf
Platform: UNKNOWN
Classifier: Development Status :: 4 - Beta
Classifier: License :: OSI Approved :: MIT License
Classifier: Programming Language :: Python :: 3.7
Classifier: Programming Language :: Python :: 3.8
